tt_lcd_common/__init__.py
tt_lcd_common/log.py
tt_lcd_common-0.2.4.dist-info/LICENSE
tt_lcd_common-0.2.4.dist-info/METADATA
tt_lcd_common-0.2.4.dist-info/WHEEL
tt_lcd_common-0.2.4.dist-info/top_level.txt
tt_lcd_common-0.2.4.dist-info/RECORD
